{
  "id": "唐门",
  "name": "唐门",
  "team": "townsfolk",
  "teamLabelZh": "镇民",
  "folder": "townsfolks",
  "variantCount": 1,
  "totalOccurrenceCount": 1,
  "variants": [
    {
      "id": "唐门",
      "name": "唐门",
      "variantIndex": 1,
      "team": "townsfolk",
      "teams": [
        "townsfolk"
      ],
      "ability": "你和弃徒之间顺时针方向上的一名善良玩家中毒。每个白天，你可以拜访说书人回答一个问题，你会得知你回答的有多准确，当你首次得知“完美”时，因你的能力中毒的玩家恢复健康。[+弃徒]",
      "image": "https://oss.gstonegames.com/data_file/clocktower/upload/202408/c_0376377752271_40a9bdd3.jpg",
      "firstNight": 0,
      "firstNightReminder": "",
      "otherNight": 0,
      "otherNightReminder": "",
      "reminders": [
        "中毒"
      ],
      "remindersGlobal": [],
      "setup": 1,
      "flavor": "针翎钉棘十指牵，暴雨飞星乾坤颠。",
      "occurrenceCount": 1,
      "notes": []
    }
  ]
}
