{
  "id": "将军",
  "name": "将军",
  "team": "townsfolk",
  "teamLabelZh": "镇民",
  "folder": "townsfolks",
  "variantCount": 23,
  "totalOccurrenceCount": 90,
  "variants": [
    {
      "id": "将军",
      "name": "将军",
      "variantIndex": 1,
      "team": "townsfolk",
      "teams": [
        "townsfolk"
      ],
      "ability": "每个夜晚，你会得知说书人认为哪个阵营当前更有优势（善良/邪恶/均势）。",
      "image": "https://oss.gstonegames.com/data_file/clocktower/web/icons/general.png",
      "firstNight": 63,
      "firstNightReminder": "唤醒将军，对他用手势比划当前的优势阵营。",
      "otherNight": 99,
      "otherNightReminder": "唤醒将军，对他用手势比划当前的优势阵营。",
      "reminders": [],
      "remindersGlobal": [],
      "setup": 0,
      "flavor": "",
      "occurrenceCount": 36,
      "notes": []
    },
    {
      "id": "将军",
      "name": "将军",
      "variantIndex": 2,
      "team": "townsfolk",
      "teams": [
        "townsfolk"
      ],
      "ability": "每个夜晚，你会得知说书人认为哪个阵营当前更有优势（善良/邪恶/均势）。",
      "image": "https://oss.gstonegames.com/data_file/clocktower/web/icons/general.png",
      "firstNight": 49,
      "firstNightReminder": "告诉将军你认为的答案。",
      "otherNight": 69,
      "otherNightReminder": "告诉将军你认为的答案。",
      "reminders": [],
      "remindersGlobal": [],
      "setup": 0,
      "flavor": "",
      "occurrenceCount": 15,
      "notes": []
    },
    {
      "id": "将军",
      "name": "将军",
      "variantIndex": 3,
      "team": "townsfolk",
      "teams": [
        "townsfolk"
      ],
      "ability": "每个夜晚，你会得知说书人认为哪个阵营当前更有优势（善良/邪恶/均势）。",
      "image": "https://oss.gstonegames.com/data_file/clocktower/role_icon/general.png",
      "firstNight": 123,
      "firstNightReminder": "告诉将军你认为的答案。",
      "otherNight": 147,
      "otherNightReminder": "告诉将军你认为的答案。",
      "reminders": [],
      "remindersGlobal": [],
      "setup": 0,
      "flavor": "",
      "occurrenceCount": 11,
      "notes": []
    },
    {
      "id": "将军",
      "name": "将军",
      "variantIndex": 4,
      "team": "townsfolk",
      "teams": [
        "townsfolk"
      ],
      "ability": "每个夜晚，你会得知说书人认为哪个阵营当前更有优势（善良/邪恶/均势）。",
      "image": "https://oss.gstonegames.com/data_file/clocktower/role_icon/general.png",
      "firstNight": 12300,
      "firstNightReminder": "告诉将军你认为的答案。",
      "otherNight": 14700,
      "otherNightReminder": "告诉将军你认为的答案。",
      "reminders": [],
      "remindersGlobal": [],
      "setup": 0,
      "flavor": "",
      "occurrenceCount": 5,
      "notes": []
    },
    {
      "id": "将军",
      "name": "将军",
      "variantIndex": 5,
      "team": "townsfolk",
      "teams": [
        "townsfolk"
      ],
      "ability": "每个夜晚，你会得知说书人认为哪个阵营当前更有优势（善良/邪恶/均势）。",
      "image": "https://oss.gstonegames.com/data_file/clocktower/role_icon/general.png",
      "firstNight": 49,
      "firstNightReminder": "告诉将军你认为的答案。",
      "otherNight": 69,
      "otherNightReminder": "告诉将军你认为的答案。",
      "reminders": [],
      "remindersGlobal": [],
      "setup": 0,
      "flavor": "",
      "occurrenceCount": 4,
      "notes": []
    },
    {
      "id": "将军",
      "name": "将军",
      "variantIndex": 6,
      "team": "townsfolk",
      "teams": [
        "townsfolk"
      ],
      "ability": "每个夜晚，你会得知说书人认为哪个阵营当前更有优势（善良/邪恶/均势）。",
      "image": "https://clocktower-wiki.gstonegames.com/images/thumb/6/6d/General.png/300px-General.png",
      "firstNight": 49,
      "firstNightReminder": "告诉将军你认为的答案。",
      "otherNight": 69,
      "otherNightReminder": "告诉将军你认为的答案。",
      "reminders": [],
      "remindersGlobal": [],
      "setup": 0,
      "flavor": "",
      "occurrenceCount": 2,
      "notes": []
    },
    {
      "id": "将军",
      "name": "将军",
      "variantIndex": 7,
      "team": "townsfolk",
      "teams": [
        "townsfolk"
      ],
      "ability": "每个夜晚，你会得知说书人认为哪个阵营当前更有优势（善良/邪恶/均势）。",
      "image": "https://www.bloodstar.xyz/p/Jungle/QiongQi/_qiongqi.png",
      "firstNight": 13,
      "firstNightReminder": "对将军展示：用拇指向上代表善良优势、向下代表邪恶优势、两边代表双方均势。",
      "otherNight": 9,
      "otherNightReminder": "对将军展示：用拇指向上代表善良优势、向下代表邪恶优势、两边代表双方均势。",
      "reminders": [],
      "remindersGlobal": [],
      "setup": 0,
      "flavor": "",
      "occurrenceCount": 1,
      "notes": []
    },
    {
      "id": "将军",
      "name": "将军",
      "variantIndex": 8,
      "team": "townsfolk",
      "teams": [
        "townsfolk"
      ],
      "ability": "每个夜晚，你会得知说书人认为哪个阵营当前更有优势（善良/邪恶/均势）。",
      "image": "https://oss.gstonegames.com/data_file/clocktower/role_icon/general.png",
      "firstNight": 21,
      "firstNightReminder": "唤醒将军，对他用手势比划当前的优势阵营。",
      "otherNight": 16,
      "otherNightReminder": "唤醒将军，对他用手势比划当前的优势阵营。",
      "reminders": [],
      "remindersGlobal": [],
      "setup": 0,
      "flavor": "",
      "occurrenceCount": 1,
      "notes": []
    },
    {
      "id": "将军",
      "name": "将军",
      "variantIndex": 9,
      "team": "townsfolk",
      "teams": [
        "townsfolk"
      ],
      "ability": "每个夜晚，你会得知说书人认为哪个阵营当前更有优势（善良/邪恶/均势）。",
      "image": "https://www.bloodstar.xyz/p/Guiltier/yi/6_yi.png",
      "firstNight": 22,
      "firstNightReminder": "唤醒将军，用手势来告知他哪个阵营处于优势。",
      "otherNight": 14,
      "otherNightReminder": "唤醒将军，用手势来告知他哪个阵营处于优势。",
      "reminders": [],
      "remindersGlobal": [],
      "setup": 0,
      "flavor": "",
      "occurrenceCount": 1,
      "notes": []
    },
    {
      "id": "将军",
      "name": "将军",
      "variantIndex": 10,
      "team": "townsfolk",
      "teams": [
        "townsfolk"
      ],
      "ability": "每个夜晚，你会得知说书人认为哪个阵营当前更有优势（善良/邪恶/均势）。",
      "image": "https://oss.gstonegames.com/data_file/clocktower/web/icons/general.png",
      "firstNight": 23,
      "firstNightReminder": "对将军展示：用拇指向上代表善良优势、向下代表邪恶优势、两边代表双方均势。",
      "otherNight": 19,
      "otherNightReminder": "对将军展示：用拇指向上代表善良优势、向下代表邪恶优势、两边代表双方均势。",
      "reminders": [],
      "remindersGlobal": [],
      "setup": 0,
      "flavor": "",
      "occurrenceCount": 1,
      "notes": []
    },
    {
      "id": "将军",
      "name": "将军",
      "variantIndex": 11,
      "team": "townsfolk",
      "teams": [
        "townsfolk"
      ],
      "ability": "每个夜晚，你会得知说书人认为哪个阵营当前更有优势（善良/邪恶/均势）。",
      "image": "https://oss.gstonegames.com/data_file/clocktower/web/icons/general.png",
      "firstNight": 3063,
      "firstNightReminder": "唤醒将军，对他用手势比划当前的优势阵营。",
      "otherNight": 99,
      "otherNightReminder": "唤醒将军，对他用手势比划当前的优势阵营。",
      "reminders": [],
      "remindersGlobal": [],
      "setup": 0,
      "flavor": "",
      "occurrenceCount": 1,
      "notes": []
    },
    {
      "id": "将军",
      "name": "将军",
      "variantIndex": 12,
      "team": "townsfolk",
      "teams": [
        "townsfolk"
      ],
      "ability": "每个夜晚，你会得知说书人认为哪个阵营当前更有优势（善良/邪恶/均势）。",
      "image": "https://patchwiki.biligame.com/images/jbzlbwgwjcygf/4/48/0gv4l35ovskh83z84qce8mikbmnpkfw.png",
      "firstNight": 3500,
      "firstNightReminder": "告诉将军你认为的答案。",
      "otherNight": 12,
      "otherNightReminder": "告诉将军你认为的答案。",
      "reminders": [],
      "remindersGlobal": [],
      "setup": 0,
      "flavor": "",
      "occurrenceCount": 1,
      "notes": []
    },
    {
      "id": "将军",
      "name": "将军",
      "variantIndex": 13,
      "team": "townsfolk",
      "teams": [
        "townsfolk"
      ],
      "ability": "每个夜晚，你会得知说书人认为哪个阵营当前更有优势（善良/邪恶/均势）。",
      "image": "https://patchwiki.biligame.com/images/jbzlbwgwjcygf/4/48/0gv4l35ovskh83z84qce8mikbmnpkfw.png",
      "firstNight": 3800,
      "firstNightReminder": "唤醒将军，对他用手势比划当前的优势阵营。",
      "otherNight": 15,
      "otherNightReminder": "唤醒将军，对他用手势比划当前的优势阵营。",
      "reminders": [],
      "remindersGlobal": [],
      "setup": 0,
      "flavor": "",
      "occurrenceCount": 1,
      "notes": []
    },
    {
      "id": "将军",
      "name": "将军",
      "variantIndex": 14,
      "team": "townsfolk",
      "teams": [
        "townsfolk"
      ],
      "ability": "每个夜晚，你会得知说书人认为哪个阵营当前更有优势（善良/邪恶/均势）。",
      "image": "https://oss.gstonegames.com/data_file/clocktower/web/icons/general.png",
      "firstNight": 3900,
      "firstNightReminder": "告诉将军你认为的答案。",
      "otherNight": 9,
      "otherNightReminder": "告诉将军你认为的答案。",
      "reminders": [],
      "remindersGlobal": [],
      "setup": 0,
      "flavor": "",
      "occurrenceCount": 1,
      "notes": []
    },
    {
      "id": "将军",
      "name": "将军",
      "variantIndex": 15,
      "team": "townsfolk",
      "teams": [
        "townsfolk"
      ],
      "ability": "每个夜晚，你会得知说书人认为哪个阵营当前更有优势（善良/邪恶/均势）。",
      "image": "https://patchwiki.biligame.com/images/jbzlbwgwjcygf/4/48/0gv4l35ovskh83z84qce8mikbmnpkfw.png",
      "firstNight": 4000,
      "firstNightReminder": "唤醒将军，对他用手势比划当前的优势阵营。",
      "otherNight": 17,
      "otherNightReminder": "唤醒将军，对他用手势比划当前的优势阵营。",
      "reminders": [],
      "remindersGlobal": [],
      "setup": 0,
      "flavor": "",
      "occurrenceCount": 1,
      "notes": []
    },
    {
      "id": "将军",
      "name": "将军",
      "variantIndex": 16,
      "team": "townsfolk",
      "teams": [
        "townsfolk"
      ],
      "ability": "每个夜晚，你会得知说书人认为哪个阵营当前更有优势（善良/邪恶/均势）。",
      "image": "https://patchwiki.biligame.com/images/jbzlbwgwjcygf/4/48/0gv4l35ovskh83z84qce8mikbmnpkfw.png",
      "firstNight": 4100,
      "firstNightReminder": "告诉将军你认为的答案。",
      "otherNight": 16,
      "otherNightReminder": "告诉将军你认为的答案。",
      "reminders": [],
      "remindersGlobal": [],
      "setup": 0,
      "flavor": "",
      "occurrenceCount": 1,
      "notes": []
    },
    {
      "id": "将军",
      "name": "将军",
      "variantIndex": 17,
      "team": "townsfolk",
      "teams": [
        "townsfolk"
      ],
      "ability": "每个夜晚，你会得知说书人认为哪个阵营当前更有优势（善良/邪恶/均势）。",
      "image": "https://patchwiki.biligame.com/images/jbzlbwgwjcygf/4/48/0gv4l35ovskh83z84qce8mikbmnpkfw.png",
      "firstNight": 4100,
      "firstNightReminder": "唤醒将军，对他用手势比划当前的优势阵营。",
      "otherNight": 22,
      "otherNightReminder": "唤醒将军，对他用手势比划当前的优势阵营。",
      "reminders": [],
      "remindersGlobal": [],
      "setup": 0,
      "flavor": "",
      "occurrenceCount": 1,
      "notes": []
    },
    {
      "id": "将军",
      "name": "将军",
      "variantIndex": 18,
      "team": "townsfolk",
      "teams": [
        "townsfolk"
      ],
      "ability": "每个夜晚，你会得知说书人认为哪个阵营当前更有优势（善良/邪恶/均势）。",
      "image": "https://oss.gstonegames.com/data_file/clocktower/web/icons/general.png",
      "firstNight": 4200,
      "firstNightReminder": "唤醒将军，对他用手势比划当前的优势阵营。",
      "otherNight": 16,
      "otherNightReminder": "唤醒将军，对他用手势比划当前的优势阵营。",
      "reminders": [],
      "remindersGlobal": [],
      "setup": 0,
      "flavor": "",
      "occurrenceCount": 1,
      "notes": []
    },
    {
      "id": "将军",
      "name": "将军",
      "variantIndex": 19,
      "team": "townsfolk",
      "teams": [
        "townsfolk"
      ],
      "ability": "每个夜晚，你会得知说书人认为哪个阵营当前更有优势（善良/邪恶/均势）。",
      "image": "https://oss.gstonegames.com/data_file/clocktower/web/icons/general.png",
      "firstNight": 4600,
      "firstNightReminder": "唤醒将军，对他用手势比划当前的优势阵营。",
      "otherNight": 17,
      "otherNightReminder": "唤醒将军，对他用手势比划当前的优势阵营。",
      "reminders": [],
      "remindersGlobal": [],
      "setup": 0,
      "flavor": "",
      "occurrenceCount": 1,
      "notes": []
    },
    {
      "id": "将军",
      "name": "将军",
      "variantIndex": 20,
      "team": "townsfolk",
      "teams": [
        "townsfolk"
      ],
      "ability": "每个夜晚，你会得知说书人认为哪个阵营当前更有优势（善良/邪恶/均势）。",
      "image": "https://oss.gstonegames.com/data_file/clocktower/web/icons/general.png",
      "firstNight": 4800,
      "firstNightReminder": "唤醒将军，对他用手势比划当前的优势阵营。",
      "otherNight": 35,
      "otherNightReminder": "唤醒将军，对他用手势比划当前的优势阵营。",
      "reminders": [],
      "remindersGlobal": [],
      "setup": 0,
      "flavor": "",
      "occurrenceCount": 1,
      "notes": []
    },
    {
      "id": "将军",
      "name": "将军",
      "variantIndex": 21,
      "team": "townsfolk",
      "teams": [
        "townsfolk"
      ],
      "ability": "每个夜晚，你会得知说书人认为哪个阵营当前更有优势（善良/邪恶/均势）。",
      "image": "https://oss.gstonegames.com/data_file/clocktower/web/icons/general.png",
      "firstNight": 6300,
      "firstNightReminder": "唤醒将军，对他用手势比划当前的优势阵营。",
      "otherNight": 99,
      "otherNightReminder": "唤醒将军，对他用手势比划当前的优势阵营。",
      "reminders": [],
      "remindersGlobal": [],
      "setup": 0,
      "flavor": "",
      "occurrenceCount": 1,
      "notes": []
    },
    {
      "id": "将军",
      "name": "将军",
      "variantIndex": 22,
      "team": "townsfolk",
      "teams": [
        "townsfolk"
      ],
      "ability": "每个夜晚，你会得知说书人认为哪个阵营当前更有优势（善良/邪恶/均势）。",
      "image": "https://oss.gstonegames.com/data_file/clocktower/web/icons/general.png",
      "firstNight": 12300,
      "firstNightReminder": "唤醒将军，对他用手势比划当前的优势阵营。",
      "otherNight": 14700,
      "otherNightReminder": "唤醒将军，对他用手势比划当前的优势阵营。",
      "reminders": [],
      "remindersGlobal": [],
      "setup": 0,
      "flavor": "",
      "occurrenceCount": 1,
      "notes": []
    },
    {
      "id": "将军",
      "name": "将军",
      "variantIndex": 23,
      "team": "townsfolk",
      "teams": [
        "townsfolk"
      ],
      "ability": "每个夜晚，你会得知说书人认为哪个阵营当前更有优势（善良/邪恶/均势）。",
      "image": "https://oss.gstonegames.com/data_file/clocktower/web/icons/general.png",
      "firstNight": 12300,
      "firstNightReminder": "对将军展示：用拇指向上代表善良优势、向下代表邪恶优势、两边代表双方均势。",
      "otherNight": 14700,
      "otherNightReminder": "对将军展示：用拇指向上代表善良优势、向下代表邪恶优势、两边代表双方均势。",
      "reminders": [],
      "remindersGlobal": [],
      "setup": 0,
      "flavor": "",
      "occurrenceCount": 1,
      "notes": []
    }
  ]
}
