{
  "id": "小提琴家",
  "name": "小提琴家",
  "team": "townsfolk",
  "teamLabelZh": "镇民",
  "folder": "townsfolks",
  "variantCount": 1,
  "totalOccurrenceCount": 1,
  "variants": [
    {
      "id": "小提琴家",
      "name": "小提琴家",
      "variantIndex": 1,
      "team": "townsfolk",
      "teams": [
        "townsfolk"
      ],
      "ability": "如果邪恶玩家杀死了你，所有邪恶玩家会醉酒到明天夜晚结束时。",
      "image": "https://www.bloodstar.xyz/p/Imzecorella/Day_By_Day/violinist_day_by_day.png",
      "firstNight": 0,
      "firstNightReminder": "",
      "otherNight": 0,
      "otherNightReminder": "如果邪恶玩家以任何方式杀死了小提琴手，放置“邪恶醉酒”提示标记到魔典中央以提示所有邪恶玩家醉酒。",
      "reminders": [
        "邪恶醉酒"
      ],
      "remindersGlobal": [],
      "setup": 0,
      "flavor": "",
      "occurrenceCount": 1,
      "notes": []
    }
  ]
}
