{
  "id": "幸存者",
  "name": "幸存者",
  "team": "townsfolk",
  "totalOccurrenceCount": 1,
  "notes": [],
  "variants": {
    "ability": [
      "在你的首个夜晚，你得知有哪些邪恶角色在场。你可能会被当作邪恶阵营、爪牙角色或恶魔角色。"
    ],
    "image": [
      "https://www.bloodstar.xyz/p/Essler/The_Delta_Expedition/remnant_the_delta_expedition.png"
    ],
    "firstNight": [
      19
    ],
    "firstNightReminder": [
      "你得知哪个邪恶角色在场。"
    ],
    "otherNight": [
      0
    ],
    "otherNightReminder": [
      ""
    ],
    "reminders": [
      []
    ],
    "remindersGlobal": [
      []
    ],
    "setup": [
      0
    ],
    "flavor": [
      "It's about time someone showed up! You have no idea what we're dealing with here."
    ]
  }
}
