{
  "id": "调查记者",
  "name": "调查记者",
  "team": "townsfolk",
  "teamLabelZh": "镇民",
  "folder": "townsfolks",
  "variantCount": 1,
  "totalOccurrenceCount": 1,
  "variants": [
    {
      "id": "调查记者",
      "name": "调查记者",
      "variantIndex": 1,
      "team": "townsfolk",
      "teams": [
        "townsfolk"
      ],
      "ability": "每个夜晚*，你要选择除你以外的一名存活玩家：破晓时，你会得知与他邻近的两名存活玩家中不存在哪两种角色类型。",
      "image": "https://oss.gstonegames.com/data_file/clocktower/upload/1691596247_197011_3292.png",
      "firstNight": 0,
      "firstNightReminder": "",
      "otherNight": 22,
      "otherNightReminder": "让调查记者选择一名其他存活玩家，用“调查”标记那名玩家。破晓时再次唤醒调查记者，告诉与那名玩家邻近的存活玩家中不存在哪两种角色类型。",
      "reminders": [
        "调查"
      ],
      "remindersGlobal": [],
      "setup": 0,
      "flavor": "",
      "occurrenceCount": 1,
      "notes": []
    }
  ]
}
