{
  "team": "demon",
  "folder": "demons",
  "characterCount": 514,
  "totalOccurrenceCount": 2945,
  "characters": [
    {
      "id": "小恶魔",
      "name": "小恶魔",
      "team": "demon",
      "totalOccurrenceCount": 232
    },
    {
      "id": "诺-达鲺",
      "name": "诺-达鲺",
      "team": "demon",
      "totalOccurrenceCount": 194
    },
    {
      "id": "亡骨魔",
      "name": "亡骨魔",
      "team": "demon",
      "totalOccurrenceCount": 188
    },
    {
      "id": "方古",
      "name": "方古",
      "team": "demon",
      "totalOccurrenceCount": 183
    },
    {
      "id": "普卡",
      "name": "普卡",
      "team": "demon",
      "totalOccurrenceCount": 153
    },
    {
      "id": "涡流",
      "name": "涡流",
      "team": "demon",
      "totalOccurrenceCount": 137
    },
    {
      "id": "珀",
      "name": "珀",
      "team": "demon",
      "totalOccurrenceCount": 114
    },
    {
      "id": "小怪宝",
      "name": "小怪宝",
      "team": "demon",
      "totalOccurrenceCount": 103
    },
    {
      "id": "痢蛭",
      "name": "痢蛭",
      "team": "demon",
      "totalOccurrenceCount": 102
    },
    {
      "id": "奥赫",
      "name": "奥赫",
      "team": "demon",
      "totalOccurrenceCount": 101
    },
    {
      "id": "卡扎力",
      "name": "卡扎力",
      "team": "demon",
      "totalOccurrenceCount": 88
    },
    {
      "id": "军团",
      "name": "军团",
      "team": "demon",
      "totalOccurrenceCount": 71
    },
    {
      "id": "牙噶巴卜",
      "name": "牙噶巴卜",
      "team": "demon",
      "totalOccurrenceCount": 71
    },
    {
      "id": "混沌",
      "name": "混沌",
      "team": "demon",
      "totalOccurrenceCount": 61
    },
    {
      "id": "饕餮",
      "name": "饕餮",
      "team": "demon",
      "totalOccurrenceCount": 57
    },
    {
      "id": "沙巴洛斯",
      "name": "沙巴洛斯",
      "team": "demon",
      "totalOccurrenceCount": 51
    },
    {
      "id": "哈迪寂亚",
      "name": "哈迪寂亚",
      "team": "demon",
      "totalOccurrenceCount": 50
    },
    {
      "id": "堤丰之首",
      "name": "堤丰之首",
      "team": "demon",
      "totalOccurrenceCount": 45
    },
    {
      "id": "姑获鸟",
      "name": "姑获鸟",
      "team": "demon",
      "totalOccurrenceCount": 44
    },
    {
      "id": "僵怖",
      "name": "僵怖",
      "team": "demon",
      "totalOccurrenceCount": 40
    },
    {
      "id": "典狱长",
      "name": "典狱长",
      "team": "demon",
      "totalOccurrenceCount": 39
    },
    {
      "id": "暴君",
      "name": "暴君",
      "team": "demon",
      "totalOccurrenceCount": 36
    },
    {
      "id": "穷奇",
      "name": "穷奇",
      "team": "demon",
      "totalOccurrenceCount": 32
    },
    {
      "id": "利维坦",
      "name": "利维坦",
      "team": "demon",
      "totalOccurrenceCount": 25
    },
    {
      "id": "暴乱",
      "name": "暴乱",
      "team": "demon",
      "totalOccurrenceCount": 25
    },
    {
      "id": "阎罗",
      "name": "阎罗",
      "team": "demon",
      "totalOccurrenceCount": 23
    },
    {
      "id": "梼杌",
      "name": "梼杌",
      "team": "demon",
      "totalOccurrenceCount": 21
    },
    {
      "id": "奸佞",
      "name": "奸佞",
      "team": "demon",
      "totalOccurrenceCount": 20
    },
    {
      "id": "镜中魔",
      "name": "镜中魔",
      "team": "demon",
      "totalOccurrenceCount": 7
    },
    {
      "id": "莉莉丝",
      "name": "莉莉丝",
      "team": "demon",
      "totalOccurrenceCount": 6
    },
    {
      "id": "刻耳柏洛斯",
      "name": "刻耳柏洛斯",
      "team": "demon",
      "totalOccurrenceCount": 5
    },
    {
      "id": "失忆的恶魔",
      "name": "失忆的恶魔",
      "team": "demon",
      "totalOccurrenceCount": 5
    },
    {
      "id": "提普-提普",
      "name": "提普-提普",
      "team": "demon",
      "totalOccurrenceCount": 5
    },
    {
      "id": "海德拉",
      "name": "海德拉",
      "team": "demon",
      "totalOccurrenceCount": 5
    },
    {
      "id": "西西弗斯",
      "name": "西西弗斯",
      "team": "demon",
      "totalOccurrenceCount": 5
    },
    {
      "id": "三威之力",
      "name": "三威之力",
      "team": "demon",
      "totalOccurrenceCount": 4
    },
    {
      "id": "塞壬",
      "name": "塞壬",
      "team": "demon",
      "totalOccurrenceCount": 4
    },
    {
      "id": "浪劫",
      "name": "浪劫",
      "team": "demon",
      "totalOccurrenceCount": 4
    },
    {
      "id": "狂戮",
      "name": "狂戮",
      "team": "demon",
      "totalOccurrenceCount": 4
    },
    {
      "id": "献礼",
      "name": "献礼",
      "team": "demon",
      "totalOccurrenceCount": 4
    },
    {
      "id": "九头蛇",
      "name": "九头蛇",
      "team": "demon",
      "totalOccurrenceCount": 3
    },
    {
      "id": "亚瑟王",
      "name": "亚瑟王",
      "team": "demon",
      "totalOccurrenceCount": 3
    },
    {
      "id": "人质先生",
      "name": "人质先生",
      "team": "demon",
      "totalOccurrenceCount": 3
    },
    {
      "id": "别西卜",
      "name": "别西卜",
      "team": "demon",
      "totalOccurrenceCount": 3
    },
    {
      "id": "半巫妖",
      "name": "半巫妖",
      "team": "demon",
      "totalOccurrenceCount": 3
    },
    {
      "id": "命运终点站",
      "name": "命运终点站",
      "team": "demon",
      "totalOccurrenceCount": 3
    },
    {
      "id": "夏柯怀特",
      "name": "夏柯怀特",
      "team": "demon",
      "totalOccurrenceCount": 3
    },
    {
      "id": "多罗迈特",
      "name": "多罗迈特",
      "team": "demon",
      "totalOccurrenceCount": 3
    },
    {
      "id": "大巫妖",
      "name": "大巫妖",
      "team": "demon",
      "totalOccurrenceCount": 3
    },
    {
      "id": "大灰狼",
      "name": "大灰狼",
      "team": "demon",
      "totalOccurrenceCount": 3
    },
    {
      "id": "奇奇默克",
      "name": "奇奇默克",
      "team": "demon",
      "totalOccurrenceCount": 3
    },
    {
      "id": "尤格萨隆",
      "name": "尤格萨隆",
      "team": "demon",
      "totalOccurrenceCount": 3
    },
    {
      "id": "尸佛",
      "name": "尸佛",
      "team": "demon",
      "totalOccurrenceCount": 3
    },
    {
      "id": "恶之花",
      "name": "恶之花",
      "team": "demon",
      "totalOccurrenceCount": 3
    },
    {
      "id": "恶堕",
      "name": "恶堕",
      "team": "demon",
      "totalOccurrenceCount": 3
    },
    {
      "id": "朋友游戏",
      "name": "朋友游戏",
      "team": "demon",
      "totalOccurrenceCount": 3
    },
    {
      "id": "枯木",
      "name": "枯木",
      "team": "demon",
      "totalOccurrenceCount": 3
    },
    {
      "id": "海拉",
      "name": "海拉",
      "team": "demon",
      "totalOccurrenceCount": 3
    },
    {
      "id": "皮影戏坊主",
      "name": "皮影戏坊主",
      "team": "demon",
      "totalOccurrenceCount": 3
    },
    {
      "id": "神言",
      "name": "神言",
      "team": "demon",
      "totalOccurrenceCount": 3
    },
    {
      "id": "长安红茶",
      "name": "长安红茶",
      "team": "demon",
      "totalOccurrenceCount": 3
    },
    {
      "id": "齐纳克",
      "name": "齐纳克",
      "team": "demon",
      "totalOccurrenceCount": 3
    },
    {
      "id": "▲小恶魔",
      "name": "▲小恶魔",
      "team": "demon",
      "totalOccurrenceCount": 2
    },
    {
      "id": "亡骨魔（改）",
      "name": "亡骨魔（改）",
      "team": "demon",
      "totalOccurrenceCount": 2
    },
    {
      "id": "人皮妖阿玲",
      "name": "人皮妖阿玲",
      "team": "demon",
      "totalOccurrenceCount": 2
    },
    {
      "id": "伽迪斯",
      "name": "伽迪斯",
      "team": "demon",
      "totalOccurrenceCount": 2
    },
    {
      "id": "佐迪翁",
      "name": "佐迪翁",
      "team": "demon",
      "totalOccurrenceCount": 2
    },
    {
      "id": "余火",
      "name": "余火",
      "team": "demon",
      "totalOccurrenceCount": 2
    },
    {
      "id": "假面特工",
      "name": "假面特工",
      "team": "demon",
      "totalOccurrenceCount": 2
    },
    {
      "id": "冤",
      "name": "冤",
      "team": "demon",
      "totalOccurrenceCount": 2
    },
    {
      "id": "凤",
      "name": "凤",
      "team": "demon",
      "totalOccurrenceCount": 2
    },
    {
      "id": "变量",
      "name": "变量",
      "team": "demon",
      "totalOccurrenceCount": 2
    },
    {
      "id": "吊死鬼珍珍",
      "name": "吊死鬼珍珍",
      "team": "demon",
      "totalOccurrenceCount": 2
    },
    {
      "id": "大将",
      "name": "大将",
      "team": "demon",
      "totalOccurrenceCount": 2
    },
    {
      "id": "天气之子",
      "name": "天气之子",
      "team": "demon",
      "totalOccurrenceCount": 2
    },
    {
      "id": "天魔",
      "name": "天魔",
      "team": "demon",
      "totalOccurrenceCount": 2
    },
    {
      "id": "天龙教",
      "name": "天龙教",
      "team": "demon",
      "totalOccurrenceCount": 2
    },
    {
      "id": "奇美拉",
      "name": "奇美拉",
      "team": "demon",
      "totalOccurrenceCount": 2
    },
    {
      "id": "女士",
      "name": "女士",
      "team": "demon",
      "totalOccurrenceCount": 2
    },
    {
      "id": "岁",
      "name": "岁",
      "team": "demon",
      "totalOccurrenceCount": 2
    },
    {
      "id": "巴洛-弗",
      "name": "巴洛-弗",
      "team": "demon",
      "totalOccurrenceCount": 2
    },
    {
      "id": "惠斯普",
      "name": "惠斯普",
      "team": "demon",
      "totalOccurrenceCount": 2
    },
    {
      "id": "拉普拉斯",
      "name": "拉普拉斯",
      "team": "demon",
      "totalOccurrenceCount": 2
    },
    {
      "id": "无常",
      "name": "无常",
      "team": "demon",
      "totalOccurrenceCount": 2
    },
    {
      "id": "树妖",
      "name": "树妖",
      "team": "demon",
      "totalOccurrenceCount": 2
    },
    {
      "id": "桑芙寂",
      "name": "桑芙寂",
      "team": "demon",
      "totalOccurrenceCount": 2
    },
    {
      "id": "死之握",
      "name": "死之握",
      "team": "demon",
      "totalOccurrenceCount": 2
    },
    {
      "id": "残念",
      "name": "残念",
      "team": "demon",
      "totalOccurrenceCount": 2
    },
    {
      "id": "活体病毒",
      "name": "活体病毒",
      "team": "demon",
      "totalOccurrenceCount": 2
    },
    {
      "id": "烈阳炽葵",
      "name": "烈阳炽葵",
      "team": "demon",
      "totalOccurrenceCount": 2
    },
    {
      "id": "烛阴",
      "name": "烛阴",
      "team": "demon",
      "totalOccurrenceCount": 2
    },
    {
      "id": "白无常",
      "name": "白无常",
      "team": "demon",
      "totalOccurrenceCount": 2
    },
    {
      "id": "白骨军团",
      "name": "白骨军团",
      "team": "demon",
      "totalOccurrenceCount": 2
    },
    {
      "id": "盟主",
      "name": "盟主",
      "team": "demon",
      "totalOccurrenceCount": 2
    },
    {
      "id": "碾骨魔",
      "name": "碾骨魔",
      "team": "demon",
      "totalOccurrenceCount": 2
    },
    {
      "id": "空间大盗",
      "name": "空间大盗",
      "team": "demon",
      "totalOccurrenceCount": 2
    },
    {
      "id": "绣刃领袖",
      "name": "绣刃领袖",
      "team": "demon",
      "totalOccurrenceCount": 2
    },
    {
      "id": "绮月",
      "name": "绮月",
      "team": "demon",
      "totalOccurrenceCount": 2
    },
    {
      "id": "耶梦加得",
      "name": "耶梦加得",
      "team": "demon",
      "totalOccurrenceCount": 2
    },
    {
      "id": "芬里尔",
      "name": "芬里尔",
      "team": "demon",
      "totalOccurrenceCount": 2
    },
    {
      "id": "芭芭雅嘎",
      "name": "芭芭雅嘎",
      "team": "demon",
      "totalOccurrenceCount": 2
    },
    {
      "id": "苏尔特尔",
      "name": "苏尔特尔",
      "team": "demon",
      "totalOccurrenceCount": 2
    },
    {
      "id": "范扎兹",
      "name": "范扎兹",
      "team": "demon",
      "totalOccurrenceCount": 2
    },
    {
      "id": "荆棘",
      "name": "荆棘",
      "team": "demon",
      "totalOccurrenceCount": 2
    },
    {
      "id": "藏镜人",
      "name": "藏镜人",
      "team": "demon",
      "totalOccurrenceCount": 2
    },
    {
      "id": "蚀疫魔",
      "name": "蚀疫魔",
      "team": "demon",
      "totalOccurrenceCount": 2
    },
    {
      "id": "血腥玛丽",
      "name": "血腥玛丽",
      "team": "demon",
      "totalOccurrenceCount": 2
    },
    {
      "id": "议",
      "name": "议",
      "team": "demon",
      "totalOccurrenceCount": 2
    },
    {
      "id": "诺-达鲺（改）",
      "name": "诺-达鲺（改）",
      "team": "demon",
      "totalOccurrenceCount": 2
    },
    {
      "id": "谎言女王",
      "name": "谎言女王",
      "team": "demon",
      "totalOccurrenceCount": 2
    },
    {
      "id": "贾巴沃克",
      "name": "贾巴沃克",
      "team": "demon",
      "totalOccurrenceCount": 2
    },
    {
      "id": "超新星",
      "name": "超新星",
      "team": "demon",
      "totalOccurrenceCount": 2
    },
    {
      "id": "路西法",
      "name": "路西法",
      "team": "demon",
      "totalOccurrenceCount": 2
    },
    {
      "id": "连环杀手",
      "name": "连环杀手",
      "team": "demon",
      "totalOccurrenceCount": 2
    },
    {
      "id": "邪祭司",
      "name": "邪祭司",
      "team": "demon",
      "totalOccurrenceCount": 2
    },
    {
      "id": "邪童阳阳",
      "name": "邪童阳阳",
      "team": "demon",
      "totalOccurrenceCount": 2
    },
    {
      "id": "锈刃领袖",
      "name": "锈刃领袖",
      "team": "demon",
      "totalOccurrenceCount": 2
    },
    {
      "id": "门之钥",
      "name": "门之钥",
      "team": "demon",
      "totalOccurrenceCount": 2
    },
    {
      "id": "阴兵",
      "name": "阴兵",
      "team": "demon",
      "totalOccurrenceCount": 2
    },
    {
      "id": "食梦貘",
      "name": "食梦貘",
      "team": "demon",
      "totalOccurrenceCount": 2
    },
    {
      "id": "鬼",
      "name": "鬼",
      "team": "demon",
      "totalOccurrenceCount": 2
    },
    {
      "id": "鸯",
      "name": "鸯",
      "team": "demon",
      "totalOccurrenceCount": 2
    },
    {
      "id": "鸳",
      "name": "鸳",
      "team": "demon",
      "totalOccurrenceCount": 2
    },
    {
      "id": "黑无常",
      "name": "黑无常",
      "team": "demon",
      "totalOccurrenceCount": 2
    },
    {
      "id": "黑美人",
      "name": "黑美人",
      "team": "demon",
      "totalOccurrenceCount": 2
    },
    {
      "id": "EM星人",
      "name": "EM星人",
      "team": "demon",
      "totalOccurrenceCount": 1
    },
    {
      "id": "X先生",
      "name": "X先生",
      "team": "demon",
      "totalOccurrenceCount": 1
    },
    {
      "id": "[数据删除]",
      "name": "[数据删除]",
      "team": "demon",
      "totalOccurrenceCount": 1
    },
    {
      "id": "“伏行混沌”奈亚拉托提普",
      "name": "“伏行混沌”奈亚拉托提普",
      "team": "demon",
      "totalOccurrenceCount": 1
    },
    {
      "id": "“剧作家”",
      "name": "“剧作家”",
      "team": "demon",
      "totalOccurrenceCount": 1
    },
    {
      "id": "“拉莱耶之主”克苏鲁",
      "name": "“拉莱耶之主”克苏鲁",
      "team": "demon",
      "totalOccurrenceCount": 1
    },
    {
      "id": "“至高母神”莎布-尼古拉丝",
      "name": "“至高母神”莎布-尼古拉丝",
      "team": "demon",
      "totalOccurrenceCount": 1
    },
    {
      "id": "“门之钥”犹格-索托斯",
      "name": "“门之钥”犹格-索托斯",
      "team": "demon",
      "totalOccurrenceCount": 1
    },
    {
      "id": "“阿米娅”，炉芯终曲",
      "name": "“阿米娅”，炉芯终曲",
      "team": "demon",
      "totalOccurrenceCount": 1
    },
    {
      "id": "▲亡骨魔",
      "name": "▲亡骨魔",
      "team": "demon",
      "totalOccurrenceCount": 1
    },
    {
      "id": "▲奥赫",
      "name": "▲奥赫",
      "team": "demon",
      "totalOccurrenceCount": 1
    },
    {
      "id": "▲姑获鸟",
      "name": "▲姑获鸟",
      "team": "demon",
      "totalOccurrenceCount": 1
    },
    {
      "id": "▲普卡",
      "name": "▲普卡",
      "team": "demon",
      "totalOccurrenceCount": 1
    },
    {
      "id": "一枕黄粱",
      "name": "一枕黄粱",
      "team": "demon",
      "totalOccurrenceCount": 1
    },
    {
      "id": "万钧之力",
      "name": "万钧之力",
      "team": "demon",
      "totalOccurrenceCount": 1
    },
    {
      "id": "三叉龙",
      "name": "三叉龙",
      "team": "demon",
      "totalOccurrenceCount": 1
    },
    {
      "id": "三尸娘娘",
      "name": "三尸娘娘",
      "team": "demon",
      "totalOccurrenceCount": 1
    },
    {
      "id": "三毒鹳",
      "name": "三毒鹳",
      "team": "demon",
      "totalOccurrenceCount": 1
    },
    {
      "id": "上古魔龙",
      "name": "上古魔龙",
      "team": "demon",
      "totalOccurrenceCount": 1
    },
    {
      "id": "不朽",
      "name": "不朽",
      "team": "demon",
      "totalOccurrenceCount": 1
    },
    {
      "id": "不死者",
      "name": "不死者",
      "team": "demon",
      "totalOccurrenceCount": 1
    },
    {
      "id": "专业杀手",
      "name": "专业杀手",
      "team": "demon",
      "totalOccurrenceCount": 1
    },
    {
      "id": "丝西娜",
      "name": "丝西娜",
      "team": "demon",
      "totalOccurrenceCount": 1
    },
    {
      "id": "丧尸",
      "name": "丧尸",
      "team": "demon",
      "totalOccurrenceCount": 1
    },
    {
      "id": "丧彪",
      "name": "丧彪",
      "team": "demon",
      "totalOccurrenceCount": 1
    },
    {
      "id": "乌纳佐斯",
      "name": "乌纳佐斯",
      "team": "demon",
      "totalOccurrenceCount": 1
    },
    {
      "id": "乔纳·马格鲁斯",
      "name": "乔纳·马格鲁斯",
      "team": "demon",
      "totalOccurrenceCount": 1
    },
    {
      "id": "九千岁",
      "name": "九千岁",
      "team": "demon",
      "totalOccurrenceCount": 1
    },
    {
      "id": "九尾",
      "name": "九尾",
      "team": "demon",
      "totalOccurrenceCount": 1
    },
    {
      "id": "九尾狐",
      "name": "九尾狐",
      "team": "demon",
      "totalOccurrenceCount": 1
    },
    {
      "id": "九鼎公",
      "name": "九鼎公",
      "team": "demon",
      "totalOccurrenceCount": 1
    },
    {
      "id": "二重身",
      "name": "二重身",
      "team": "demon",
      "totalOccurrenceCount": 1
    },
    {
      "id": "亚煞极",
      "name": "亚煞极",
      "team": "demon",
      "totalOccurrenceCount": 1
    },
    {
      "id": "亡命徒",
      "name": "亡命徒",
      "team": "demon",
      "totalOccurrenceCount": 1
    },
    {
      "id": "亡魂",
      "name": "亡魂",
      "team": "demon",
      "totalOccurrenceCount": 1
    },
    {
      "id": "伊斯巴达登",
      "name": "伊斯巴达登",
      "team": "demon",
      "totalOccurrenceCount": 1
    },
    {
      "id": "伊祖米克的子代",
      "name": "伊祖米克的子代",
      "team": "demon",
      "totalOccurrenceCount": 1
    },
    {
      "id": "伊祖米克，生态源泉",
      "name": "伊祖米克，生态源泉",
      "team": "demon",
      "totalOccurrenceCount": 1
    },
    {
      "id": "伏地魔",
      "name": "伏地魔",
      "team": "demon",
      "totalOccurrenceCount": 1
    },
    {
      "id": "众生堂",
      "name": "众生堂",
      "team": "demon",
      "totalOccurrenceCount": 1
    },
    {
      "id": "作曲家",
      "name": "作曲家",
      "team": "demon",
      "totalOccurrenceCount": 1
    },
    {
      "id": "侩子手",
      "name": "侩子手",
      "team": "demon",
      "totalOccurrenceCount": 1
    },
    {
      "id": "保王党",
      "name": "保王党",
      "team": "demon",
      "totalOccurrenceCount": 1
    },
    {
      "id": "信念",
      "name": "信念",
      "team": "demon",
      "totalOccurrenceCount": 1
    },
    {
      "id": "偏执",
      "name": "偏执",
      "team": "demon",
      "totalOccurrenceCount": 1
    },
    {
      "id": "傩戏班",
      "name": "傩戏班",
      "team": "demon",
      "totalOccurrenceCount": 1
    },
    {
      "id": "催眠师",
      "name": "催眠师",
      "team": "demon",
      "totalOccurrenceCount": 1
    },
    {
      "id": "僵怖（改）",
      "name": "僵怖（改）",
      "team": "demon",
      "totalOccurrenceCount": 1
    },
    {
      "id": "克拉肯R",
      "name": "克拉肯R",
      "team": "demon",
      "totalOccurrenceCount": 1
    },
    {
      "id": "克拉苏",
      "name": "克拉苏",
      "team": "demon",
      "totalOccurrenceCount": 1
    },
    {
      "id": "克苏恩",
      "name": "克苏恩",
      "team": "demon",
      "totalOccurrenceCount": 1
    },
    {
      "id": "克苏鲁",
      "name": "克苏鲁",
      "team": "demon",
      "totalOccurrenceCount": 1
    },
    {
      "id": "克里奥佩特拉",
      "name": "克里奥佩特拉",
      "team": "demon",
      "totalOccurrenceCount": 1
    },
    {
      "id": "全视之眼",
      "name": "全视之眼",
      "team": "demon",
      "totalOccurrenceCount": 1
    },
    {
      "id": "八咫乌",
      "name": "八咫乌",
      "team": "demon",
      "totalOccurrenceCount": 1
    },
    {
      "id": "八岐大蛇",
      "name": "八岐大蛇",
      "team": "demon",
      "totalOccurrenceCount": 1
    },
    {
      "id": "六六六",
      "name": "六六六",
      "team": "demon",
      "totalOccurrenceCount": 1
    },
    {
      "id": "兽皮玩偶",
      "name": "兽皮玩偶",
      "team": "demon",
      "totalOccurrenceCount": 1
    },
    {
      "id": "冢中枯骨",
      "name": "冢中枯骨",
      "team": "demon",
      "totalOccurrenceCount": 1
    },
    {
      "id": "冰之女皇",
      "name": "冰之女皇",
      "team": "demon",
      "totalOccurrenceCount": 1
    },
    {
      "id": "冷杉老人",
      "name": "冷杉老人",
      "team": "demon",
      "totalOccurrenceCount": 1
    },
    {
      "id": "准小恶魔",
      "name": "准小恶魔",
      "team": "demon",
      "totalOccurrenceCount": 1
    },
    {
      "id": "凯撒",
      "name": "凯撒",
      "team": "demon",
      "totalOccurrenceCount": 1
    },
    {
      "id": "列车惯性",
      "name": "列车惯性",
      "team": "demon",
      "totalOccurrenceCount": 1
    },
    {
      "id": "别西格鲁夫",
      "name": "别西格鲁夫",
      "team": "demon",
      "totalOccurrenceCount": 1
    },
    {
      "id": "刺客",
      "name": "刺客",
      "team": "demon",
      "totalOccurrenceCount": 1
    },
    {
      "id": "刻耳帕洛斯",
      "name": "刻耳帕洛斯",
      "team": "demon",
      "totalOccurrenceCount": 1
    },
    {
      "id": "勒西弗",
      "name": "勒西弗",
      "team": "demon",
      "totalOccurrenceCount": 1
    },
    {
      "id": "千面人",
      "name": "千面人",
      "team": "demon",
      "totalOccurrenceCount": 1
    },
    {
      "id": "半兽人",
      "name": "半兽人",
      "team": "demon",
      "totalOccurrenceCount": 1
    },
    {
      "id": "卓尔卡尼斯",
      "name": "卓尔卡尼斯",
      "team": "demon",
      "totalOccurrenceCount": 1
    },
    {
      "id": "博士",
      "name": "博士",
      "team": "demon",
      "totalOccurrenceCount": 1
    },
    {
      "id": "卡吕普索C",
      "name": "卡吕普索C",
      "team": "demon",
      "totalOccurrenceCount": 1
    },
    {
      "id": "卡巴拉",
      "name": "卡巴拉",
      "team": "demon",
      "totalOccurrenceCount": 1
    },
    {
      "id": "卢基诺",
      "name": "卢基诺",
      "team": "demon",
      "totalOccurrenceCount": 1
    },
    {
      "id": "卸磨杀驴",
      "name": "卸磨杀驴",
      "team": "demon",
      "totalOccurrenceCount": 1
    },
    {
      "id": "原初",
      "name": "原初",
      "team": "demon",
      "totalOccurrenceCount": 1
    },
    {
      "id": "双头蛟",
      "name": "双头蛟",
      "team": "demon",
      "totalOccurrenceCount": 1
    },
    {
      "id": "反同杀手",
      "name": "反同杀手",
      "team": "demon",
      "totalOccurrenceCount": 1
    },
    {
      "id": "反法同盟",
      "name": "反法同盟",
      "team": "demon",
      "totalOccurrenceCount": 1
    },
    {
      "id": "反社会人格",
      "name": "反社会人格",
      "team": "demon",
      "totalOccurrenceCount": 1
    },
    {
      "id": "变幻海灵",
      "name": "变幻海灵",
      "team": "demon",
      "totalOccurrenceCount": 1
    },
    {
      "id": "变相怪杰",
      "name": "变相怪杰",
      "team": "demon",
      "totalOccurrenceCount": 1
    },
    {
      "id": "古夫纳",
      "name": "古夫纳",
      "team": "demon",
      "totalOccurrenceCount": 1
    },
    {
      "id": "史矛革",
      "name": "史矛革",
      "team": "demon",
      "totalOccurrenceCount": 1
    },
    {
      "id": "合奏团",
      "name": "合奏团",
      "team": "demon",
      "totalOccurrenceCount": 1
    },
    {
      "id": "吟游诗人",
      "name": "吟游诗人",
      "team": "demon",
      "totalOccurrenceCount": 1
    },
    {
      "id": "启示录",
      "name": "启示录",
      "team": "demon",
      "totalOccurrenceCount": 1
    },
    {
      "id": "吵闹鬼",
      "name": "吵闹鬼",
      "team": "demon",
      "totalOccurrenceCount": 1
    },
    {
      "id": "吸血鬼精灵",
      "name": "吸血鬼精灵",
      "team": "demon",
      "totalOccurrenceCount": 1
    },
    {
      "id": "呓语之球",
      "name": "呓语之球",
      "team": "demon",
      "totalOccurrenceCount": 1
    },
    {
      "id": "咒",
      "name": "咒",
      "team": "demon",
      "totalOccurrenceCount": 1
    },
    {
      "id": "咒魂",
      "name": "咒魂",
      "team": "demon",
      "totalOccurrenceCount": 1
    },
    {
      "id": "哈兰杜汗，大地之鞭",
      "name": "哈兰杜汗，大地之鞭",
      "team": "demon",
      "totalOccurrenceCount": 1
    },
    {
      "id": "哈斯塔",
      "name": "哈斯塔",
      "team": "demon",
      "totalOccurrenceCount": 1
    },
    {
      "id": "哈米吉多顿",
      "name": "哈米吉多顿",
      "team": "demon",
      "totalOccurrenceCount": 1
    },
    {
      "id": "喧闹鬼",
      "name": "喧闹鬼",
      "team": "demon",
      "totalOccurrenceCount": 1
    },
    {
      "id": "噩梦凶灵",
      "name": "噩梦凶灵",
      "team": "demon",
      "totalOccurrenceCount": 1
    },
    {
      "id": "回魂太上皇",
      "name": "回魂太上皇",
      "team": "demon",
      "totalOccurrenceCount": 1
    },
    {
      "id": "圣诞怪杰",
      "name": "圣诞怪杰",
      "team": "demon",
      "totalOccurrenceCount": 1
    },
    {
      "id": "地下医生",
      "name": "地下医生",
      "team": "demon",
      "totalOccurrenceCount": 1
    },
    {
      "id": "地城领主",
      "name": "地城领主",
      "team": "demon",
      "totalOccurrenceCount": 1
    },
    {
      "id": "地狱业火",
      "name": "地狱业火",
      "team": "demon",
      "totalOccurrenceCount": 1
    },
    {
      "id": "场地工",
      "name": "场地工",
      "team": "demon",
      "totalOccurrenceCount": 1
    },
    {
      "id": "复仇同妻",
      "name": "复仇同妻",
      "team": "demon",
      "totalOccurrenceCount": 1
    },
    {
      "id": "多玛姆",
      "name": "多玛姆",
      "team": "demon",
      "totalOccurrenceCount": 1
    },
    {
      "id": "多米诺",
      "name": "多米诺",
      "team": "demon",
      "totalOccurrenceCount": 1
    },
    {
      "id": "夜阎魔",
      "name": "夜阎魔",
      "team": "demon",
      "totalOccurrenceCount": 1
    },
    {
      "id": "夜魇",
      "name": "夜魇",
      "team": "demon",
      "totalOccurrenceCount": 1
    },
    {
      "id": "大天狗",
      "name": "大天狗",
      "team": "demon",
      "totalOccurrenceCount": 1
    },
    {
      "id": "大恶魔",
      "name": "大恶魔",
      "team": "demon",
      "totalOccurrenceCount": 1
    },
    {
      "id": "天下人",
      "name": "天下人",
      "team": "demon",
      "totalOccurrenceCount": 1
    },
    {
      "id": "天灾",
      "name": "天灾",
      "team": "demon",
      "totalOccurrenceCount": 1
    },
    {
      "id": "天狗",
      "name": "天狗",
      "team": "demon",
      "totalOccurrenceCount": 1
    },
    {
      "id": "天谴·Damnation",
      "name": "天谴·Damnation",
      "team": "demon",
      "totalOccurrenceCount": 1
    },
    {
      "id": "天道",
      "name": "天道",
      "team": "demon",
      "totalOccurrenceCount": 1
    },
    {
      "id": "天道化身",
      "name": "天道化身",
      "team": "demon",
      "totalOccurrenceCount": 1
    },
    {
      "id": "天龙",
      "name": "天龙",
      "team": "demon",
      "totalOccurrenceCount": 1
    },
    {
      "id": "太后",
      "name": "太后",
      "team": "demon",
      "totalOccurrenceCount": 1
    },
    {
      "id": "太阳黑子",
      "name": "太阳黑子",
      "team": "demon",
      "totalOccurrenceCount": 1
    },
    {
      "id": "奈亚拉托提普",
      "name": "奈亚拉托提普",
      "team": "demon",
      "totalOccurrenceCount": 1
    },
    {
      "id": "奈亚拉托提普的化身",
      "name": "奈亚拉托提普的化身",
      "team": "demon",
      "totalOccurrenceCount": 1
    },
    {
      "id": "奈落魔",
      "name": "奈落魔",
      "team": "demon",
      "totalOccurrenceCount": 1
    },
    {
      "id": "奥创",
      "name": "奥创",
      "team": "demon",
      "totalOccurrenceCount": 1
    },
    {
      "id": "奥喇剌",
      "name": "奥喇剌",
      "team": "demon",
      "totalOccurrenceCount": 1
    },
    {
      "id": "女帝",
      "name": "女帝",
      "team": "demon",
      "totalOccurrenceCount": 1
    },
    {
      "id": "女王蜂*",
      "name": "女王蜂*",
      "team": "demon",
      "totalOccurrenceCount": 1
    },
    {
      "id": "女皇",
      "name": "女皇",
      "team": "demon",
      "totalOccurrenceCount": 1
    },
    {
      "id": "妄想乐园",
      "name": "妄想乐园",
      "team": "demon",
      "totalOccurrenceCount": 1
    },
    {
      "id": "妖怪",
      "name": "妖怪",
      "team": "demon",
      "totalOccurrenceCount": 1
    },
    {
      "id": "孺蚀公",
      "name": "孺蚀公",
      "team": "demon",
      "totalOccurrenceCount": 1
    },
    {
      "id": "安",
      "name": "安",
      "team": "demon",
      "totalOccurrenceCount": 1
    },
    {
      "id": "安德拉斯",
      "name": "安德拉斯",
      "team": "demon",
      "totalOccurrenceCount": 1
    },
    {
      "id": "审问者",
      "name": "审问者",
      "team": "demon",
      "totalOccurrenceCount": 1
    },
    {
      "id": "寂灭",
      "name": "寂灭",
      "team": "demon",
      "totalOccurrenceCount": 1
    },
    {
      "id": "寄生者",
      "name": "寄生者",
      "team": "demon",
      "totalOccurrenceCount": 1
    },
    {
      "id": "小恶龙",
      "name": "小恶龙",
      "team": "demon",
      "totalOccurrenceCount": 1
    },
    {
      "id": "尸解仙",
      "name": "尸解仙",
      "team": "demon",
      "totalOccurrenceCount": 1
    },
    {
      "id": "巨眼",
      "name": "巨眼",
      "team": "demon",
      "totalOccurrenceCount": 1
    },
    {
      "id": "巫-隗",
      "name": "巫-隗",
      "team": "demon",
      "totalOccurrenceCount": 1
    },
    {
      "id": "巫妖",
      "name": "巫妖",
      "team": "demon",
      "totalOccurrenceCount": 1
    },
    {
      "id": "希望",
      "name": "希望",
      "team": "demon",
      "totalOccurrenceCount": 1
    },
    {
      "id": "幽灵",
      "name": "幽灵",
      "team": "demon",
      "totalOccurrenceCount": 1
    },
    {
      "id": "幽荧·烛照",
      "name": "幽荧·烛照",
      "team": "demon",
      "totalOccurrenceCount": 1
    },
    {
      "id": "广寒灵",
      "name": "广寒灵",
      "team": "demon",
      "totalOccurrenceCount": 1
    },
    {
      "id": "库克夸 ¶",
      "name": "库克夸 ¶",
      "team": "demon",
      "totalOccurrenceCount": 1
    },
    {
      "id": "库洛普斯",
      "name": "库洛普斯",
      "team": "demon",
      "totalOccurrenceCount": 1
    },
    {
      "id": "开心猴",
      "name": "开心猴",
      "team": "demon",
      "totalOccurrenceCount": 1
    },
    {
      "id": "当权者",
      "name": "当权者",
      "team": "demon",
      "totalOccurrenceCount": 1
    },
    {
      "id": "德古拉",
      "name": "德古拉",
      "team": "demon",
      "totalOccurrenceCount": 1
    },
    {
      "id": "德拉科尼",
      "name": "德拉科尼",
      "team": "demon",
      "totalOccurrenceCount": 1
    },
    {
      "id": "德泽贝尔",
      "name": "德泽贝尔",
      "team": "demon",
      "totalOccurrenceCount": 1
    },
    {
      "id": "怪物书",
      "name": "怪物书",
      "team": "demon",
      "totalOccurrenceCount": 1
    },
    {
      "id": "恐同份子",
      "name": "恐同份子",
      "team": "demon",
      "totalOccurrenceCount": 1
    },
    {
      "id": "恐帝",
      "name": "恐帝",
      "team": "demon",
      "totalOccurrenceCount": 1
    },
    {
      "id": "恩佐斯",
      "name": "恩佐斯",
      "team": "demon",
      "totalOccurrenceCount": 1
    },
    {
      "id": "恶瞳",
      "name": "恶瞳",
      "team": "demon",
      "totalOccurrenceCount": 1
    },
    {
      "id": "恶魔之子",
      "name": "恶魔之子",
      "team": "demon",
      "totalOccurrenceCount": 1
    },
    {
      "id": "悬崖深渊",
      "name": "悬崖深渊",
      "team": "demon",
      "totalOccurrenceCount": 1
    },
    {
      "id": "悲剧演员",
      "name": "悲剧演员",
      "team": "demon",
      "totalOccurrenceCount": 1
    },
    {
      "id": "惨绝戏子",
      "name": "惨绝戏子",
      "team": "demon",
      "totalOccurrenceCount": 1
    },
    {
      "id": "战争",
      "name": "战争",
      "team": "demon",
      "totalOccurrenceCount": 1
    },
    {
      "id": "扎布·亚尼",
      "name": "扎布·亚尼",
      "team": "demon",
      "totalOccurrenceCount": 1
    },
    {
      "id": "扫把星",
      "name": "扫把星",
      "team": "demon",
      "totalOccurrenceCount": 1
    },
    {
      "id": "扼杀梦想家",
      "name": "扼杀梦想家",
      "team": "demon",
      "totalOccurrenceCount": 1
    },
    {
      "id": "拉克沙萨",
      "name": "拉克沙萨",
      "team": "demon",
      "totalOccurrenceCount": 1
    },
    {
      "id": "拘魂官",
      "name": "拘魂官",
      "team": "demon",
      "totalOccurrenceCount": 1
    },
    {
      "id": "持久大1",
      "name": "持久大1",
      "team": "demon",
      "totalOccurrenceCount": 1
    },
    {
      "id": "指挥家",
      "name": "指挥家",
      "team": "demon",
      "totalOccurrenceCount": 1
    },
    {
      "id": "指点江山",
      "name": "指点江山",
      "team": "demon",
      "totalOccurrenceCount": 1
    },
    {
      "id": "捕食植物",
      "name": "捕食植物",
      "team": "demon",
      "totalOccurrenceCount": 1
    },
    {
      "id": "撒旦老人",
      "name": "撒旦老人",
      "team": "demon",
      "totalOccurrenceCount": 1
    },
    {
      "id": "救赎·Salvation",
      "name": "救赎·Salvation",
      "team": "demon",
      "totalOccurrenceCount": 1
    },
    {
      "id": "敖钦",
      "name": "敖钦",
      "team": "demon",
      "totalOccurrenceCount": 1
    },
    {
      "id": "敖闰",
      "name": "敖闰",
      "team": "demon",
      "totalOccurrenceCount": 1
    },
    {
      "id": "敖顺",
      "name": "敖顺",
      "team": "demon",
      "totalOccurrenceCount": 1
    },
    {
      "id": "散兵",
      "name": "散兵",
      "team": "demon",
      "totalOccurrenceCount": 1
    },
    {
      "id": "斐斯特伍德",
      "name": "斐斯特伍德",
      "team": "demon",
      "totalOccurrenceCount": 1
    },
    {
      "id": "斯克恩",
      "name": "斯克恩",
      "team": "demon",
      "totalOccurrenceCount": 1
    },
    {
      "id": "斯塔特勒",
      "name": "斯塔特勒",
      "team": "demon",
      "totalOccurrenceCount": 1
    },
    {
      "id": "新世界秩序",
      "name": "新世界秩序",
      "team": "demon",
      "totalOccurrenceCount": 1
    },
    {
      "id": "族长",
      "name": "族长",
      "team": "demon",
      "totalOccurrenceCount": 1
    },
    {
      "id": "无名",
      "name": "无名",
      "team": "demon",
      "totalOccurrenceCount": 1
    },
    {
      "id": "无影",
      "name": "无影",
      "team": "demon",
      "totalOccurrenceCount": 1
    },
    {
      "id": "无生老母",
      "name": "无生老母",
      "team": "demon",
      "totalOccurrenceCount": 1
    },
    {
      "id": "无量仙翁",
      "name": "无量仙翁",
      "team": "demon",
      "totalOccurrenceCount": 1
    },
    {
      "id": "日月神教",
      "name": "日月神教",
      "team": "demon",
      "totalOccurrenceCount": 1
    },
    {
      "id": "旱魃",
      "name": "旱魃",
      "team": "demon",
      "totalOccurrenceCount": 1
    },
    {
      "id": "时间旅人",
      "name": "时间旅人",
      "team": "demon",
      "totalOccurrenceCount": 1
    },
    {
      "id": "明教",
      "name": "明教",
      "team": "demon",
      "totalOccurrenceCount": 1
    },
    {
      "id": "昔拉",
      "name": "昔拉",
      "team": "demon",
      "totalOccurrenceCount": 1
    },
    {
      "id": "春夏秋冬",
      "name": "春夏秋冬",
      "team": "demon",
      "totalOccurrenceCount": 1
    },
    {
      "id": "春秋笔",
      "name": "春秋笔",
      "team": "demon",
      "totalOccurrenceCount": 1
    },
    {
      "id": "普卡（改）",
      "name": "普卡（改）",
      "team": "demon",
      "totalOccurrenceCount": 1
    },
    {
      "id": "暗杀一族",
      "name": "暗杀一族",
      "team": "demon",
      "totalOccurrenceCount": 1
    },
    {
      "id": "曼塞尔",
      "name": "曼塞尔",
      "team": "demon",
      "totalOccurrenceCount": 1
    },
    {
      "id": "最终恶魔",
      "name": "最终恶魔",
      "team": "demon",
      "totalOccurrenceCount": 1
    },
    {
      "id": "未知存在体",
      "name": "未知存在体",
      "team": "demon",
      "totalOccurrenceCount": 1
    },
    {
      "id": "末日执行者",
      "name": "末日执行者",
      "team": "demon",
      "totalOccurrenceCount": 1
    },
    {
      "id": "本影",
      "name": "本影",
      "team": "demon",
      "totalOccurrenceCount": 1
    },
    {
      "id": "朱雀",
      "name": "朱雀",
      "team": "demon",
      "totalOccurrenceCount": 1
    },
    {
      "id": "机械大军",
      "name": "机械大军",
      "team": "demon",
      "totalOccurrenceCount": 1
    },
    {
      "id": "机械师",
      "name": "机械师",
      "team": "demon",
      "totalOccurrenceCount": 1
    },
    {
      "id": "朽木",
      "name": "朽木",
      "team": "demon",
      "totalOccurrenceCount": 1
    },
    {
      "id": "样本#006",
      "name": "样本#006",
      "team": "demon",
      "totalOccurrenceCount": 1
    },
    {
      "id": "格格巫",
      "name": "格格巫",
      "team": "demon",
      "totalOccurrenceCount": 1
    },
    {
      "id": "格特鲁德·罗宾森",
      "name": "格特鲁德·罗宾森",
      "team": "demon",
      "totalOccurrenceCount": 1
    },
    {
      "id": "桑格莉娅",
      "name": "桑格莉娅",
      "team": "demon",
      "totalOccurrenceCount": 1
    },
    {
      "id": "档案员",
      "name": "档案员",
      "team": "demon",
      "totalOccurrenceCount": 1
    },
    {
      "id": "梦",
      "name": "梦",
      "team": "demon",
      "totalOccurrenceCount": 1
    },
    {
      "id": "梦之土蜘蛛",
      "name": "梦之土蜘蛛",
      "team": "demon",
      "totalOccurrenceCount": 1
    },
    {
      "id": "植育者",
      "name": "植育者",
      "team": "demon",
      "totalOccurrenceCount": 1
    },
    {
      "id": "死亡圣神",
      "name": "死亡圣神",
      "team": "demon",
      "totalOccurrenceCount": 1
    },
    {
      "id": "死兆星",
      "name": "死兆星",
      "team": "demon",
      "totalOccurrenceCount": 1
    },
    {
      "id": "死神",
      "name": "死神",
      "team": "demon",
      "totalOccurrenceCount": 1
    },
    {
      "id": "死神13",
      "name": "死神13",
      "team": "demon",
      "totalOccurrenceCount": 1
    },
    {
      "id": "残躯",
      "name": "残躯",
      "team": "demon",
      "totalOccurrenceCount": 1
    },
    {
      "id": "毒涎虫",
      "name": "毒涎虫",
      "team": "demon",
      "totalOccurrenceCount": 1
    },
    {
      "id": "汉尼拔",
      "name": "汉尼拔",
      "team": "demon",
      "totalOccurrenceCount": 1
    },
    {
      "id": "汤姆·里德尔",
      "name": "汤姆·里德尔",
      "team": "demon",
      "totalOccurrenceCount": 1
    },
    {
      "id": "沙巴洛斯（改）",
      "name": "沙巴洛斯（改）",
      "team": "demon",
      "totalOccurrenceCount": 1
    },
    {
      "id": "沼泽蜥人",
      "name": "沼泽蜥人",
      "team": "demon",
      "totalOccurrenceCount": 1
    },
    {
      "id": "波旁王朝统治",
      "name": "波旁王朝统治",
      "team": "demon",
      "totalOccurrenceCount": 1
    },
    {
      "id": "泽德拉丝",
      "name": "泽德拉丝",
      "team": "demon",
      "totalOccurrenceCount": 1
    },
    {
      "id": "泽德拉斯",
      "name": "泽德拉斯",
      "team": "demon",
      "totalOccurrenceCount": 1
    },
    {
      "id": "活幕之手",
      "name": "活幕之手",
      "team": "demon",
      "totalOccurrenceCount": 1
    },
    {
      "id": "海坊主I",
      "name": "海坊主I",
      "team": "demon",
      "totalOccurrenceCount": 1
    },
    {
      "id": "深渊",
      "name": "深渊",
      "team": "demon",
      "totalOccurrenceCount": 1
    },
    {
      "id": "温达鲁野兽",
      "name": "温达鲁野兽",
      "team": "demon",
      "totalOccurrenceCount": 1
    },
    {
      "id": "湮生之冢",
      "name": "湮生之冢",
      "team": "demon",
      "totalOccurrenceCount": 1
    },
    {
      "id": "灭霸",
      "name": "灭霸",
      "team": "demon",
      "totalOccurrenceCount": 1
    },
    {
      "id": "灵感大王",
      "name": "灵感大王",
      "team": "demon",
      "totalOccurrenceCount": 1
    },
    {
      "id": "灵魂之槌",
      "name": "灵魂之槌",
      "team": "demon",
      "totalOccurrenceCount": 1
    },
    {
      "id": "炮王",
      "name": "炮王",
      "team": "demon",
      "totalOccurrenceCount": 1
    },
    {
      "id": "烟囱",
      "name": "烟囱",
      "team": "demon",
      "totalOccurrenceCount": 1
    },
    {
      "id": "烟火师",
      "name": "烟火师",
      "team": "demon",
      "totalOccurrenceCount": 1
    },
    {
      "id": "焦尾",
      "name": "焦尾",
      "team": "demon",
      "totalOccurrenceCount": 1
    },
    {
      "id": "燃煤引擎",
      "name": "燃煤引擎",
      "team": "demon",
      "totalOccurrenceCount": 1
    },
    {
      "id": "爆炸王",
      "name": "爆炸王",
      "team": "demon",
      "totalOccurrenceCount": 1
    },
    {
      "id": "爬行眼",
      "name": "爬行眼",
      "team": "demon",
      "totalOccurrenceCount": 1
    },
    {
      "id": "爱",
      "name": "爱",
      "team": "demon",
      "totalOccurrenceCount": 1
    },
    {
      "id": "犹格-索托斯",
      "name": "犹格-索托斯",
      "team": "demon",
      "totalOccurrenceCount": 1
    },
    {
      "id": "狐仙",
      "name": "狐仙",
      "team": "demon",
      "totalOccurrenceCount": 1
    },
    {
      "id": "狐媚",
      "name": "狐媚",
      "team": "demon",
      "totalOccurrenceCount": 1
    },
    {
      "id": "狼狈为奸",
      "name": "狼狈为奸",
      "team": "demon",
      "totalOccurrenceCount": 1
    },
    {
      "id": "猪小姐",
      "name": "猪小姐",
      "team": "demon",
      "totalOccurrenceCount": 1
    },
    {
      "id": "王子",
      "name": "王子",
      "team": "demon",
      "totalOccurrenceCount": 1
    },
    {
      "id": "玛门",
      "name": "玛门",
      "team": "demon",
      "totalOccurrenceCount": 1
    },
    {
      "id": "珀西",
      "name": "珀西",
      "team": "demon",
      "totalOccurrenceCount": 1
    },
    {
      "id": "理发师",
      "name": "理发师",
      "team": "demon",
      "totalOccurrenceCount": 1
    },
    {
      "id": "瓦尔多夫",
      "name": "瓦尔多夫",
      "team": "demon",
      "totalOccurrenceCount": 1
    },
    {
      "id": "瓦尔拉文",
      "name": "瓦尔拉文",
      "team": "demon",
      "totalOccurrenceCount": 1
    },
    {
      "id": "电车难题",
      "name": "电车难题",
      "team": "demon",
      "totalOccurrenceCount": 1
    },
    {
      "id": "画家",
      "name": "画家",
      "team": "demon",
      "totalOccurrenceCount": 1
    },
    {
      "id": "瘟疫之源",
      "name": "瘟疫之源",
      "team": "demon",
      "totalOccurrenceCount": 1
    },
    {
      "id": "瘟疫骑士",
      "name": "瘟疫骑士",
      "team": "demon",
      "totalOccurrenceCount": 1
    },
    {
      "id": "瘴客",
      "name": "瘴客",
      "team": "demon",
      "totalOccurrenceCount": 1
    },
    {
      "id": "白羊黑痣",
      "name": "白羊黑痣",
      "team": "demon",
      "totalOccurrenceCount": 1
    },
    {
      "id": "白虎",
      "name": "白虎",
      "team": "demon",
      "totalOccurrenceCount": 1
    },
    {
      "id": "皇上",
      "name": "皇上",
      "team": "demon",
      "totalOccurrenceCount": 1
    },
    {
      "id": "皮克希",
      "name": "皮克希",
      "team": "demon",
      "totalOccurrenceCount": 1
    },
    {
      "id": "真小恶魔！",
      "name": "真小恶魔！",
      "team": "demon",
      "totalOccurrenceCount": 1
    },
    {
      "id": "真理之环",
      "name": "真理之环",
      "team": "demon",
      "totalOccurrenceCount": 1
    },
    {
      "id": "眼神",
      "name": "眼神",
      "team": "demon",
      "totalOccurrenceCount": 1
    },
    {
      "id": "督政府",
      "name": "督政府",
      "team": "demon",
      "totalOccurrenceCount": 1
    },
    {
      "id": "破坏者",
      "name": "破坏者",
      "team": "demon",
      "totalOccurrenceCount": 1
    },
    {
      "id": "破窗效应",
      "name": "破窗效应",
      "team": "demon",
      "totalOccurrenceCount": 1
    },
    {
      "id": "神之手",
      "name": "神之手",
      "team": "demon",
      "totalOccurrenceCount": 1
    },
    {
      "id": "神碑",
      "name": "神碑",
      "team": "demon",
      "totalOccurrenceCount": 1
    },
    {
      "id": "神秘人",
      "name": "神秘人",
      "team": "demon",
      "totalOccurrenceCount": 1
    },
    {
      "id": "童趣玩偶",
      "name": "童趣玩偶",
      "team": "demon",
      "totalOccurrenceCount": 1
    },
    {
      "id": "类小恶魔",
      "name": "类小恶魔",
      "team": "demon",
      "totalOccurrenceCount": 1
    },
    {
      "id": "精神分裂",
      "name": "精神分裂",
      "team": "demon",
      "totalOccurrenceCount": 1
    },
    {
      "id": "糖果阴谋家",
      "name": "糖果阴谋家",
      "team": "demon",
      "totalOccurrenceCount": 1
    },
    {
      "id": "索命",
      "name": "索命",
      "team": "demon",
      "totalOccurrenceCount": 1
    },
    {
      "id": "红心皇后",
      "name": "红心皇后",
      "team": "demon",
      "totalOccurrenceCount": 1
    },
    {
      "id": "红心骑士",
      "name": "红心骑士",
      "team": "demon",
      "totalOccurrenceCount": 1
    },
    {
      "id": "红月教皇",
      "name": "红月教皇",
      "team": "demon",
      "totalOccurrenceCount": 1
    },
    {
      "id": "红桃王后",
      "name": "红桃王后",
      "team": "demon",
      "totalOccurrenceCount": 1
    },
    {
      "id": "红皇后",
      "name": "红皇后",
      "team": "demon",
      "totalOccurrenceCount": 1
    },
    {
      "id": "约瑟夫",
      "name": "约瑟夫",
      "team": "demon",
      "totalOccurrenceCount": 1
    },
    {
      "id": "纳利斯之喉",
      "name": "纳利斯之喉",
      "team": "demon",
      "totalOccurrenceCount": 1
    },
    {
      "id": "纸夫人",
      "name": "纸夫人",
      "team": "demon",
      "totalOccurrenceCount": 1
    },
    {
      "id": "织夜者",
      "name": "织夜者",
      "team": "demon",
      "totalOccurrenceCount": 1
    },
    {
      "id": "结党营私",
      "name": "结党营私",
      "team": "demon",
      "totalOccurrenceCount": 1
    },
    {
      "id": "结命之网",
      "name": "结命之网",
      "team": "demon",
      "totalOccurrenceCount": 1
    },
    {
      "id": "绝命毒师",
      "name": "绝命毒师",
      "team": "demon",
      "totalOccurrenceCount": 1
    },
    {
      "id": "绝望梦魇",
      "name": "绝望梦魇",
      "team": "demon",
      "totalOccurrenceCount": 1
    },
    {
      "id": "罗刹",
      "name": "罗刹",
      "team": "demon",
      "totalOccurrenceCount": 1
    },
    {
      "id": "羽化仙",
      "name": "羽化仙",
      "team": "demon",
      "totalOccurrenceCount": 1
    },
    {
      "id": "老穷奇",
      "name": "老穷奇",
      "team": "demon",
      "totalOccurrenceCount": 1
    },
    {
      "id": "联合体",
      "name": "联合体",
      "team": "demon",
      "totalOccurrenceCount": 1
    },
    {
      "id": "肌肉公0",
      "name": "肌肉公0",
      "team": "demon",
      "totalOccurrenceCount": 1
    },
    {
      "id": "肠系魔",
      "name": "肠系魔",
      "team": "demon",
      "totalOccurrenceCount": 1
    },
    {
      "id": "背叛者",
      "name": "背叛者",
      "team": "demon",
      "totalOccurrenceCount": 1
    },
    {
      "id": "脊蛊",
      "name": "脊蛊",
      "team": "demon",
      "totalOccurrenceCount": 1
    },
    {
      "id": "腐儒",
      "name": "腐儒",
      "team": "demon",
      "totalOccurrenceCount": 1
    },
    {
      "id": "腐化之源",
      "name": "腐化之源",
      "team": "demon",
      "totalOccurrenceCount": 1
    },
    {
      "id": "腐化荆棘",
      "name": "腐化荆棘",
      "team": "demon",
      "totalOccurrenceCount": 1
    },
    {
      "id": "腐尸花",
      "name": "腐尸花",
      "team": "demon",
      "totalOccurrenceCount": 1
    },
    {
      "id": "至尊扫货",
      "name": "至尊扫货",
      "team": "demon",
      "totalOccurrenceCount": 1
    },
    {
      "id": "致命叔叔",
      "name": "致命叔叔",
      "team": "demon",
      "totalOccurrenceCount": 1
    },
    {
      "id": "般若",
      "name": "般若",
      "team": "demon",
      "totalOccurrenceCount": 1
    },
    {
      "id": "艾莫霍克",
      "name": "艾莫霍克",
      "team": "demon",
      "totalOccurrenceCount": 1
    },
    {
      "id": "芬里尔之爪",
      "name": "芬里尔之爪",
      "team": "demon",
      "totalOccurrenceCount": 1
    },
    {
      "id": "苍白之母",
      "name": "苍白之母",
      "team": "demon",
      "totalOccurrenceCount": 1
    },
    {
      "id": "苦难根源",
      "name": "苦难根源",
      "team": "demon",
      "totalOccurrenceCount": 1
    },
    {
      "id": "荒芜",
      "name": "荒芜",
      "team": "demon",
      "totalOccurrenceCount": 1
    },
    {
      "id": "莫甘娜",
      "name": "莫甘娜",
      "team": "demon",
      "totalOccurrenceCount": 1
    },
    {
      "id": "莱薇",
      "name": "莱薇",
      "team": "demon",
      "totalOccurrenceCount": 1
    },
    {
      "id": "蓓尔嘉",
      "name": "蓓尔嘉",
      "team": "demon",
      "totalOccurrenceCount": 1
    },
    {
      "id": "蔽世之影",
      "name": "蔽世之影",
      "team": "demon",
      "totalOccurrenceCount": 1
    },
    {
      "id": "虚空之神",
      "name": "虚空之神",
      "team": "demon",
      "totalOccurrenceCount": 1
    },
    {
      "id": "蛟龙",
      "name": "蛟龙",
      "team": "demon",
      "totalOccurrenceCount": 1
    },
    {
      "id": "蛮王",
      "name": "蛮王",
      "team": "demon",
      "totalOccurrenceCount": 1
    },
    {
      "id": "蠕行恐惧",
      "name": "蠕行恐惧",
      "team": "demon",
      "totalOccurrenceCount": 1
    },
    {
      "id": "血渡鸦",
      "name": "血渡鸦",
      "team": "demon",
      "totalOccurrenceCount": 1
    },
    {
      "id": "血织女",
      "name": "血织女",
      "team": "demon",
      "totalOccurrenceCount": 1
    },
    {
      "id": "行",
      "name": "行",
      "team": "demon",
      "totalOccurrenceCount": 1
    },
    {
      "id": "裁决使",
      "name": "裁决使",
      "team": "demon",
      "totalOccurrenceCount": 1
    },
    {
      "id": "西西弗斯*",
      "name": "西西弗斯*",
      "team": "demon",
      "totalOccurrenceCount": 1
    },
    {
      "id": "观",
      "name": "观",
      "team": "demon",
      "totalOccurrenceCount": 1
    },
    {
      "id": "诛心",
      "name": "诛心",
      "team": "demon",
      "totalOccurrenceCount": 1
    },
    {
      "id": "诡美人",
      "name": "诡美人",
      "team": "demon",
      "totalOccurrenceCount": 1
    },
    {
      "id": "诺·达鲺",
      "name": "诺·达鲺",
      "team": "demon",
      "totalOccurrenceCount": 1
    },
    {
      "id": "诺斯特",
      "name": "诺斯特",
      "team": "demon",
      "totalOccurrenceCount": 1
    },
    {
      "id": "豪赌客",
      "name": "豪赌客",
      "team": "demon",
      "totalOccurrenceCount": 1
    },
    {
      "id": "贝尔森克",
      "name": "贝尔森克",
      "team": "demon",
      "totalOccurrenceCount": 1
    },
    {
      "id": "贪得无厌",
      "name": "贪得无厌",
      "team": "demon",
      "totalOccurrenceCount": 1
    },
    {
      "id": "赛",
      "name": "赛",
      "team": "demon",
      "totalOccurrenceCount": 1
    },
    {
      "id": "赤色联盟",
      "name": "赤色联盟",
      "team": "demon",
      "totalOccurrenceCount": 1
    },
    {
      "id": "赫忒斯塔 ✦",
      "name": "赫忒斯塔 ✦",
      "team": "demon",
      "totalOccurrenceCount": 1
    },
    {
      "id": "赫拉",
      "name": "赫拉",
      "team": "demon",
      "totalOccurrenceCount": 1
    },
    {
      "id": "路加萨尔古斯，历法之王",
      "name": "路加萨尔古斯，历法之王",
      "team": "demon",
      "totalOccurrenceCount": 1
    },
    {
      "id": "路易十六",
      "name": "路易十六",
      "team": "demon",
      "totalOccurrenceCount": 1
    },
    {
      "id": "路比",
      "name": "路比",
      "team": "demon",
      "totalOccurrenceCount": 1
    },
    {
      "id": "躁狂症",
      "name": "躁狂症",
      "team": "demon",
      "totalOccurrenceCount": 1
    },
    {
      "id": "边狱·Limbo",
      "name": "边狱·Limbo",
      "team": "demon",
      "totalOccurrenceCount": 1
    },
    {
      "id": "迷雾",
      "name": "迷雾",
      "team": "demon",
      "totalOccurrenceCount": 1
    },
    {
      "id": "追踪者",
      "name": "追踪者",
      "team": "demon",
      "totalOccurrenceCount": 1
    },
    {
      "id": "逆命魔王",
      "name": "逆命魔王",
      "team": "demon",
      "totalOccurrenceCount": 1
    },
    {
      "id": "逆时旅人",
      "name": "逆时旅人",
      "team": "demon",
      "totalOccurrenceCount": 1
    },
    {
      "id": "造物之语",
      "name": "造物之语",
      "team": "demon",
      "totalOccurrenceCount": 1
    },
    {
      "id": "遗忘",
      "name": "遗忘",
      "team": "demon",
      "totalOccurrenceCount": 1
    },
    {
      "id": "邪恶祭典",
      "name": "邪恶祭典",
      "team": "demon",
      "totalOccurrenceCount": 1
    },
    {
      "id": "配器师",
      "name": "配器师",
      "team": "demon",
      "totalOccurrenceCount": 1
    },
    {
      "id": "铠甲骑士",
      "name": "铠甲骑士",
      "team": "demon",
      "totalOccurrenceCount": 1
    },
    {
      "id": "锅炉",
      "name": "锅炉",
      "team": "demon",
      "totalOccurrenceCount": 1
    },
    {
      "id": "阎君",
      "name": "阎君",
      "team": "demon",
      "totalOccurrenceCount": 1
    },
    {
      "id": "阖众",
      "name": "阖众",
      "team": "demon",
      "totalOccurrenceCount": 1
    },
    {
      "id": "阴魂",
      "name": "阴魂",
      "team": "demon",
      "totalOccurrenceCount": 1
    },
    {
      "id": "阿撒托斯",
      "name": "阿撒托斯",
      "team": "demon",
      "totalOccurrenceCount": 1
    },
    {
      "id": "隐形者",
      "name": "隐形者",
      "team": "demon",
      "totalOccurrenceCount": 1
    },
    {
      "id": "雅各宾派",
      "name": "雅各宾派",
      "team": "demon",
      "totalOccurrenceCount": 1
    },
    {
      "id": "集群者",
      "name": "集群者",
      "team": "demon",
      "totalOccurrenceCount": 1
    },
    {
      "id": "雇佣杀手",
      "name": "雇佣杀手",
      "team": "demon",
      "totalOccurrenceCount": 1
    },
    {
      "id": "雪人",
      "name": "雪人",
      "team": "demon",
      "totalOccurrenceCount": 1
    },
    {
      "id": "霍乱之源",
      "name": "霍乱之源",
      "team": "demon",
      "totalOccurrenceCount": 1
    },
    {
      "id": "霜害",
      "name": "霜害",
      "team": "demon",
      "totalOccurrenceCount": 1
    },
    {
      "id": "霸主",
      "name": "霸主",
      "team": "demon",
      "totalOccurrenceCount": 1
    },
    {
      "id": "霸凌者*",
      "name": "霸凌者*",
      "team": "demon",
      "totalOccurrenceCount": 1
    },
    {
      "id": "青龙",
      "name": "青龙",
      "team": "demon",
      "totalOccurrenceCount": 1
    },
    {
      "id": "非小恶魔局",
      "name": "非小恶魔局",
      "team": "demon",
      "totalOccurrenceCount": 1
    },
    {
      "id": "顺直大帝",
      "name": "顺直大帝",
      "team": "demon",
      "totalOccurrenceCount": 1
    },
    {
      "id": "领主",
      "name": "领主",
      "team": "demon",
      "totalOccurrenceCount": 1
    },
    {
      "id": "风语命轨",
      "name": "风语命轨",
      "team": "demon",
      "totalOccurrenceCount": 1
    },
    {
      "id": "飞鼠",
      "name": "飞鼠",
      "team": "demon",
      "totalOccurrenceCount": 1
    },
    {
      "id": "飞龙",
      "name": "飞龙",
      "team": "demon",
      "totalOccurrenceCount": 1
    },
    {
      "id": "食死徒",
      "name": "食死徒",
      "team": "demon",
      "totalOccurrenceCount": 1
    },
    {
      "id": "食貘",
      "name": "食貘",
      "team": "demon",
      "totalOccurrenceCount": 1
    },
    {
      "id": "飧",
      "name": "飧",
      "team": "demon",
      "totalOccurrenceCount": 1
    },
    {
      "id": "饲疫者",
      "name": "饲疫者",
      "team": "demon",
      "totalOccurrenceCount": 1
    },
    {
      "id": "骇愕兽",
      "name": "骇愕兽",
      "team": "demon",
      "totalOccurrenceCount": 1
    },
    {
      "id": "骰子大师",
      "name": "骰子大师",
      "team": "demon",
      "totalOccurrenceCount": 1
    },
    {
      "id": "骸漩",
      "name": "骸漩",
      "team": "demon",
      "totalOccurrenceCount": 1
    },
    {
      "id": "鬼婴",
      "name": "鬼婴",
      "team": "demon",
      "totalOccurrenceCount": 1
    },
    {
      "id": "魂归者",
      "name": "魂归者",
      "team": "demon",
      "totalOccurrenceCount": 1
    },
    {
      "id": "魂火",
      "name": "魂火",
      "team": "demon",
      "totalOccurrenceCount": 1
    },
    {
      "id": "魃",
      "name": "魃",
      "team": "demon",
      "totalOccurrenceCount": 1
    },
    {
      "id": "魄",
      "name": "魄",
      "team": "demon",
      "totalOccurrenceCount": 1
    },
    {
      "id": "魔王",
      "name": "魔王",
      "team": "demon",
      "totalOccurrenceCount": 1
    },
    {
      "id": "魔鬼叶",
      "name": "魔鬼叶",
      "team": "demon",
      "totalOccurrenceCount": 1
    },
    {
      "id": "魔鬼教师*",
      "name": "魔鬼教师*",
      "team": "demon",
      "totalOccurrenceCount": 1
    },
    {
      "id": "鲁萨尔卡R",
      "name": "鲁萨尔卡R",
      "team": "demon",
      "totalOccurrenceCount": 1
    },
    {
      "id": "黑山羊幼仔",
      "name": "黑山羊幼仔",
      "team": "demon",
      "totalOccurrenceCount": 1
    },
    {
      "id": "黑玫瑰",
      "name": "黑玫瑰",
      "team": "demon",
      "totalOccurrenceCount": 1
    },
    {
      "id": "鼍神",
      "name": "鼍神",
      "team": "demon",
      "totalOccurrenceCount": 1
    },
    {
      "id": "鼠王",
      "name": "鼠王",
      "team": "demon",
      "totalOccurrenceCount": 1
    },
    {
      "id": "齐'纳克",
      "name": "齐'纳克",
      "team": "demon",
      "totalOccurrenceCount": 1
    }
  ]
}
