{
  "id": "别西格鲁夫",
  "name": "别西格鲁夫",
  "team": "demon",
  "totalOccurrenceCount": 1,
  "notes": [],
  "variants": {
    "ability": [
      "每个夜晚，你要选择除你以外的两名玩家：他们明天白天不会死于处决，其中的善良玩家会在下个夜晚死亡。"
    ],
    "image": [
      "https://i.postimg.cc/qMpFcJHS/image.png"
    ],
    "firstNight": [
      32
    ],
    "firstNightReminder": [
      "让别西格鲁夫选择除自己以外的两名玩家：标记这些玩家处决不死。"
    ],
    "otherNight": [
      9
    ],
    "otherNightReminder": [
      "标记别西格鲁夫上个夜晚选择过的玩家（标有处决不死的玩家）死亡。让别西卜选择除自己以外的两名玩家：标记这些玩家处决不死。"
    ],
    "reminders": [
      [
        "处决不死",
        "选择"
      ]
    ],
    "remindersGlobal": [
      []
    ],
    "setup": [
      0
    ],
    "flavor": [
      ""
    ]
  }
}
