{
  "id": "兵",
  "name": "兵",
  "team": "outsider",
  "teamLabelZh": "外来者",
  "folder": "outsiders",
  "variantCount": 1,
  "totalOccurrenceCount": 1,
  "variants": [
    {
      "id": "兵",
      "name": "兵",
      "variantIndex": 1,
      "team": "outsider",
      "teams": [
        "outsider"
      ],
      "ability": "你拥有一个不在场的非王的镇民角色能力，但你不知道是什么。每个夜晚，你可能会被唤醒以选择玩家，即使你的能力需要每晚醒来，或者不需要醒来。",
      "image": "https://i.postimg.cc/hG5GP0tx/image.png",
      "firstNight": 0,
      "firstNightReminder": "",
      "otherNight": 0,
      "otherNightReminder": "",
      "reminders": [
        "是兵"
      ],
      "remindersGlobal": [],
      "setup": 0,
      "flavor": "",
      "occurrenceCount": 1,
      "notes": []
    }
  ]
}
