{
  "id": "姜饼人",
  "name": "姜饼人",
  "team": "traveler",
  "totalOccurrenceCount": 2,
  "notes": [],
  "variants": {
    "ability": [
      "每个夜晚，你要选择一名玩家：如果他今晚可以行动，他得知自己被你选择，并且他在你的行动结束后立即行动。"
    ],
    "image": [
      "https://i.postimg.cc/GpN3pvnC/gingerbreadman-fairy-tale.png"
    ],
    "firstNight": [
      12
    ],
    "firstNightReminder": [
      "唤醒姜饼人，让他指向一名玩家。唤醒那名玩家，向他展示“该角色能力对你生效”提示卡并展示姜饼人角色标记，并让他立刻行动。"
    ],
    "otherNight": [
      2
    ],
    "otherNightReminder": [
      "唤醒姜饼人，让他指向一名玩家。唤醒那名玩家，向他展示“该角色能力对你生效”提示卡并展示姜饼人角色标记，并让他立刻行动。"
    ],
    "reminders": [
      []
    ],
    "remindersGlobal": [
      []
    ],
    "setup": [
      0
    ],
    "flavor": [
      "快点动起来。"
    ]
  }
}
