{
  "id": "雇佣杀手",
  "name": "雇佣杀手",
  "team": "traveler",
  "totalOccurrenceCount": 1,
  "notes": [],
  "variants": {
    "ability": [
      "在白天时，你可以随时让自己失踪直到今天黄昏。每局游戏限一次，在白天时，你可以选择一名失踪的玩家（即使你已失踪）：他死亡。"
    ],
    "image": [
      "https://free.picui.cn/free/2025/11/28/69289a6d89844.png"
    ],
    "firstNight": [
      0
    ],
    "firstNightReminder": [
      ""
    ],
    "otherNight": [
      0
    ],
    "otherNightReminder": [
      ""
    ],
    "reminders": [
      [
        "失去能力",
        "失踪"
      ]
    ],
    "remindersGlobal": [
      []
    ],
    "setup": [
      0
    ],
    "flavor": [
      ""
    ]
  }
}
