{
  "id": "势利鬼",
  "name": "势利鬼",
  "team": "minion",
  "teamLabelZh": "爪牙",
  "folder": "minions",
  "variantCount": 1,
  "totalOccurrenceCount": 1,
  "variants": [
    {
      "id": "势利鬼",
      "name": "势利鬼",
      "variantIndex": 1,
      "team": "minion",
      "teams": [
        "minion"
      ],
      "ability": "如果有一名外来者死亡，一名爪牙可以选择变成一名他选择的不在场的爪牙角色。[+1外来者]",
      "image": "[\"https://i.postimg.cc/Xv0vVzxg/image.png\"]",
      "firstNight": 0,
      "firstNightReminder": "",
      "otherNight": 17,
      "otherNightReminder": "如果有一名外来者死亡, 一名爪牙可以选择变成一名他选择的不在场的爪牙角色。",
      "reminders": [
        "改头换帽"
      ],
      "remindersGlobal": [],
      "setup": 1,
      "flavor": "Ohhhhhmygod, did you *see* what Janet was wearing??? Where did she get dressed, the dumpster?",
      "occurrenceCount": 1,
      "notes": []
    }
  ]
}
