{
  "id": "噤",
  "name": "噤",
  "team": "minion",
  "teamLabelZh": "爪牙",
  "folder": "minions",
  "variantCount": 1,
  "totalOccurrenceCount": 1,
  "variants": [
    {
      "id": "噤",
      "name": "噤",
      "variantIndex": 1,
      "team": "minion",
      "teams": [
        "minion"
      ],
      "ability": "所有玩家在投票时闭眼，且票数会秘密统计，即使你已死亡。你死亡后，每次投票时可以投两票。",
      "image": "https://patchwiki.biligame.com/images/jbzlbwgwjcygf/4/4e/4keecp81p204vr5q6q6jcb44hid04qq.png",
      "firstNight": 0,
      "firstNightReminder": "",
      "otherNight": 0,
      "otherNightReminder": "",
      "reminders": [
        "嘘"
      ],
      "remindersGlobal": [],
      "setup": 0,
      "flavor": "",
      "occurrenceCount": 1,
      "notes": []
    }
  ]
}
