{
  "id": "稻草人",
  "name": "稻草人",
  "team": "minion",
  "teamLabelZh": "爪牙",
  "folder": "minions",
  "variantCount": 1,
  "totalOccurrenceCount": 1,
  "variants": [
    {
      "id": "稻草人",
      "name": "稻草人",
      "variantIndex": 1,
      "team": "minion",
      "teams": [
        "minion"
      ],
      "ability": "善良玩家会把你当作恶魔，恶魔当作爪牙。",
      "image": "https://i.postimg.cc/hvhk95DZ/image.png",
      "firstNight": 0,
      "firstNightReminder": "",
      "otherNight": 0,
      "otherNightReminder": "",
      "reminders": [
        "当作恶魔",
        "当作爪牙"
      ],
      "remindersGlobal": [],
      "setup": 0,
      "flavor": "",
      "occurrenceCount": 1,
      "notes": []
    }
  ]
}
